spanish_nlp/__about__.py
spanish_nlp/__init__.py
spanish_nlp/augmentation/__init__.py
spanish_nlp/augmentation/abstract.py
spanish_nlp/augmentation/masked.py
spanish_nlp/augmentation/spelling.py
spanish_nlp/augmentation/data/misspelled_words.json
spanish_nlp/classifiers/__init__.py
spanish_nlp/classifiers/classifiers.py
spanish_nlp/preprocess/__init__.py
spanish_nlp/preprocess/preprocess.py
spanish_nlp/spellchecker/__init__.py
spanish_nlp/spellchecker/base.py
spanish_nlp/spellchecker/contextual_lm_impl.py
spanish_nlp/spellchecker/dictionary_impl.py
"spanish_nlp/utils/__init__,py"
spanish_nlp/utils/emo_unicode.py
spanish_nlp/utils/inclusive_words.py
spanish_nlp/utils/stopwords.py
spanish_nlp/utils/tokenizers.py
spanish_nlp-0.4.0.dist-info/METADATA
spanish_nlp-0.4.0.dist-info/WHEEL
spanish_nlp-0.4.0.dist-info/licenses/LICENSE
spanish_nlp-0.4.0.dist-info/RECORD
