Metadata-Version: 2.4
Name: spanish_nlp
Version: 0.4.0
Summary: A package for NLP in Spanish
Project-URL: Homepage, https://github.com/jorgeortizfuentes/spanish_nlp
Author-email: Jorge Ortiz-Fuentes <jorge@ortizfuentes.com>
License-Expression: GPL-3.0-or-later
License-File: LICENSE
Keywords: augmentation,clasificacion,classifier,español,language,lenguaje,nlp,pln,preprocesamiento,preprocess,spanish
Classifier: Development Status :: 3 - Alpha
Classifier: Intended Audience :: Developers
Classifier: License :: OSI Approved :: GNU General Public License v3 (GPLv3)
Classifier: Operating System :: OS Independent
Classifier: Programming Language :: Python :: 3
Classifier: Programming Language :: Python :: 3.7
Classifier: Programming Language :: Python :: 3.8
Classifier: Programming Language :: Python :: 3.9
Classifier: Programming Language :: Python :: 3.10
Classifier: Topic :: Text Processing :: Linguistic
Requires-Python: >=3.8
Requires-Dist: datasets
Requires-Dist: emoji
Requires-Dist: es-core-news-sm
Requires-Dist: kaleido
Requires-Dist: nltk
Requires-Dist: pandas
Requires-Dist: torch
Requires-Dist: transformers
